getnet/__init__.py
getnet/api.py
getnet/exceptions.py
getnet/services/__init__.py
getnet/services/base.py
getnet/services/cards/__init__.py
getnet/services/cards/card.py
getnet/services/cards/card_response.py
getnet/services/cards/service.py
getnet/services/charges/__init__.py
getnet/services/charges/charge_response.py
getnet/services/charges/service.py
getnet/services/customers/__init__.py
getnet/services/customers/address.py
getnet/services/customers/customer.py
getnet/services/customers/customer_response.py
getnet/services/customers/service.py
getnet/services/payments/__init__.py
getnet/services/payments/customer.py
getnet/services/payments/order.py
getnet/services/payments/payment_response.py
getnet/services/payments/boleto/__init__.py
getnet/services/payments/boleto/boleto.py
getnet/services/payments/boleto/boleto_response.py
getnet/services/payments/boleto/service.py
getnet/services/payments/credit/__init__.py
getnet/services/payments/credit/card.py
getnet/services/payments/credit/credit.py
getnet/services/payments/credit/credit_cancel.py
getnet/services/payments/credit/credit_response.py
getnet/services/payments/credit/service.py
getnet/services/plans/__init__.py
getnet/services/plans/period.py
getnet/services/plans/plan.py
getnet/services/plans/plan_response.py
getnet/services/plans/service.py
getnet/services/subscriptions/__init__.py
getnet/services/subscriptions/card.py
getnet/services/subscriptions/credit.py
getnet/services/subscriptions/customer.py
getnet/services/subscriptions/service.py
getnet/services/subscriptions/subscription.py
getnet/services/subscriptions/subscription_response.py
getnet/services/token/__init__.py
getnet/services/token/card_number.py
getnet/services/token/card_token.py
getnet/services/token/service.py
getnet/services/utils/__init__.py
getnet/services/utils/device.py
tests/__init__.py
tests/getnet/__init__.py
tests/getnet/test_api.py
tests/getnet/services/__init__.py
tests/getnet/services/cards/__init__.py
getnet_py-1.1.1.dist-info/LICENSE
getnet_py-1.1.1.dist-info/METADATA
getnet_py-1.1.1.dist-info/WHEEL
getnet_py-1.1.1.dist-info/top_level.txt
getnet_py-1.1.1.dist-info/RECORD
