Metadata-Version: 2.1
Name: getnet-py
Version: 1.1.1
Summary: A Getnet Santander SDK
Home-page: https://github.com/ramon/getnet-py
Author: Ramon Soares
Author-email: contato@ramonsoares.com
License: UNKNOWN
Platform: UNKNOWN
Classifier: Intended Audience :: Developers
Classifier: Natural Language :: English
Classifier: License :: OSI Approved :: MIT License
Classifier: Programming Language :: Python
Classifier: Programming Language :: Python :: 3
Requires-Python: >=3.2
Requires-Dist: requests (>=2.0.0)
Requires-Dist: requests-oauthlib (>=1.2.0)
Requires-Dist: python-dateutil (==2.8.1)
